polars_cv/__init__.py
polars_cv/_graph.py
polars_cv/_graph_viz.py
polars_cv/_lib.abi3.so
polars_cv/_types.py
polars_cv/expressions.py
polars_cv/geometry/__init__.py
polars_cv/geometry/contours.py
polars_cv/geometry/points.py
polars_cv/geometry/schemas.py
polars_cv/geometry/validation.py
polars_cv/lazy.py
polars_cv/pipeline.py
polars_cv/py.typed
polars_cv-0.6.0.dist-info/METADATA
polars_cv-0.6.0.dist-info/WHEEL
polars_cv-0.6.0.dist-info/RECORD
