Metadata-Version: 2.4
Name: polars-cv
Version: 0.6.0
Classifier: Programming Language :: Rust
Classifier: Programming Language :: Python :: Implementation :: CPython
Classifier: Programming Language :: Python :: 3.9
Classifier: Programming Language :: Python :: 3.10
Classifier: Programming Language :: Python :: 3.11
Classifier: Programming Language :: Python :: 3.12
Requires-Dist: networkx>=3.4.2
Requires-Dist: numpy>=2.2.6
Requires-Dist: polars>=1.0,<2.0
Requires-Dist: graphviz>=0.21
Requires-Dist: pydot>=4.0.1
Summary: A Polars plugin for vision/array operations
Author-email: Hesham Dar <heshamdar@gmail.com>
License: MIT OR Apache-2.0
Requires-Python: >=3.10
